tfl/__init__.py
tfl/base/__init__.py
tfl/base/_base_handler.py
tfl/cli/__init__.py
tfl/cli/_async_typer.py
tfl/cli/main.py
tfl/cli/py.typed
tfl/clients/__init__.py
tfl/clients/_auth.py
tfl/clients/_client.py
tfl/clients/handlers/__init__.py
tfl/clients/handlers/_accident_stats_handler.py
tfl/clients/handlers/_air_quality_handler.py
tfl/clients/handlers/_client_handlers.py
tfl/clients/handlers/_crowding_handler.py
tfl/clients/handlers/_lift_disruptions_handler.py
tfl/clients/py.typed
tfl/enums.py
tfl/py.typed
py_tfl-0.5.0.dist-info/LICENSE
py_tfl-0.5.0.dist-info/METADATA
py_tfl-0.5.0.dist-info/WHEEL
py_tfl-0.5.0.dist-info/entry_points.txt
py_tfl-0.5.0.dist-info/RECORD
